{
  "taskDefinitionArn": "arn:aws:ecs:ap-southeast-2:184870188834:task-definition/turners-website-task:5",
  "containerDefinitions": [
      {
          "name": "turners-website",
          "image": "turners-insurance-website:latest",
          "cpu": 0,
          "links": [],
          "portMappings": [
              {
                  "containerPort": 3000,
                  "hostPort": 3000,
                  "protocol": "tcp"
              }
          ],
          "essential": true,
          "entryPoint": [],
          "command": [],
          "environment": [],
          "environmentFiles": [],
          "mountPoints": [],
          "volumesFrom": [],
          "secrets": [],
          "dnsServers": [],
          "dnsSearchDomains": [],
          "extraHosts": [],
          "dockerSecurityOptions": [],
          "dockerLabels": {},
          "ulimits": [],
          "systemControls": []
      }
  ],
  "family": "turners-website-task",
  "taskRoleArn": "arn:aws:iam::184870188834:role/ecsTaskExecutionRole",
  "networkMode": "awsvpc",
  "revision": 5,
  "volumes": [],
  "status": "ACTIVE",
  "requiresAttributes": [
      {
          "name": "com.amazonaws.ecs.capability.docker-remote-api.1.17"
      },
      {
          "name": "com.amazonaws.ecs.capability.task-iam-role"
      },
      {
          "name": "com.amazonaws.ecs.capability.docker-remote-api.1.18"
      },
      {
          "name": "ecs.capability.task-eni"
      }
  ],
  "placementConstraints": [],
  "compatibilities": [
      "EC2",
      "FARGATE"
  ],
  "runtimePlatform": {
      "cpuArchitecture": "X86_64",
      "operatingSystemFamily": "LINUX"
  },
  "requiresCompatibilities": [
      "EC2"
  ],
  "cpu": "1024",
  "memory": "3072",
  "registeredAt": "2022-03-10T03:13:06.422Z",
  "registeredBy": "arn:aws:iam::184870188834:root",
  "tags": [
      {
          "key": "ecs:taskDefinition:createdFrom",
          "value": "ecs-console-v2"
      },
      {
          "key": "ecs:taskDefinition:stackId",
          "value": "arn:aws:cloudformation:ap-southeast-2:184870188834:stack/ECS-Console-V2-TaskDefinition-e5e6d056-21ef-4de1-b15b-09da9908c56d/fdecd5f0-a01f-11ec-b30b-0afe4726a7f8"
      }
  ]
}